setup.py
bin/test-this-time.py
test_gwss/__init__.py
test_gwss.egg-info/PKG-INFO
test_gwss.egg-info/SOURCES.txt
test_gwss.egg-info/dependency_links.txt
test_gwss.egg-info/not-zip-safe
test_gwss.egg-info/requires.txt
test_gwss.egg-info/top_level.txt