Metadata-Version: 1.0
Name: test-gwss
Version: 1.8
Summary: Garena web stats system
Home-page: http://github.com/storborg/funniest
Author: Tran Minh Tri
Author-email: tranmt@garena.com
License: MIT
Platform: UNKNOWN
